workreport/__init__.py
workreport/__main__.py
workreport/cli.py
workreport/gui.py
workreport/tests/__init__.py
workreport/tests/conftest.py
workreport/tests/test_utils.py
workreport/utils.py
workreport-0.0.dist-info/entry_points.txt
workreport-0.0.dist-info/LICENSE.md
workreport-0.0.dist-info/WHEEL
workreport-0.0.dist-info/METADATA
workreport-0.0.dist-info/RECORD
